subdownloader/__init__.py
subdownloader/callback.py
subdownloader/filescan.py
subdownloader/identification.py
subdownloader/metadata.py
subdownloader/movie.py
subdownloader/project.py
subdownloader/query.py
subdownloader/subtitle2.py
subdownloader/util.py
subdownloader/video2.py
subdownloader/webutil.py
subdownloader/client/__init__.py
subdownloader/client/__main__.py
subdownloader/client/arguments.py
subdownloader/client/callback.py
subdownloader/client/configuration.py
subdownloader/client/internationalization.py
subdownloader/client/logger.py
subdownloader/client/state.py
subdownloader/client/user_agent.py
subdownloader/client/cli/__init__.py
subdownloader/client/cli/callback.py
subdownloader/client/cli/cli.py
subdownloader/client/cli/state.py
subdownloader/client/gui/__init__.py
subdownloader/client/gui/callback.py
subdownloader/client/gui/state.py
subdownloader/client/gui/generated/__init__.py
subdownloader/client/gui/generated/about_ui.py
subdownloader/client/gui/generated/images_rc.py
subdownloader/client/gui/generated/imdbSearch_ui.py
subdownloader/client/gui/generated/login_ui.py
subdownloader/client/gui/generated/main_ui.py
subdownloader/client/gui/generated/preferences_ui.py
subdownloader/client/gui/generated/searchFileWidget_ui.py
subdownloader/client/gui/generated/searchNameWidget_ui.py
subdownloader/client/gui/generated/uploadWidget_ui.py
subdownloader/client/gui/models/__init__.py
subdownloader/client/gui/models/imdbSearchModel.py
subdownloader/client/gui/models/language.py
subdownloader/client/gui/models/searchFileModel.py
subdownloader/client/gui/models/searchNameModel.py
subdownloader/client/gui/models/upload.py
subdownloader/client/gui/views/__init__.py
subdownloader/client/gui/views/imdb.py
subdownloader/client/gui/views/language.py
subdownloader/client/gui/views/upload.py
subdownloader/client/gui/widgets/__init__.py
subdownloader/client/gui/widgets/about.py
subdownloader-2.1.0.dist-info/DESCRIPTION.rst
subdownloader-2.1.0.dist-info/LICENSE.txt
subdownloader-2.1.0.dist-info/METADATA
subdownloader-2.1.0.dist-info/RECORD
subdownloader-2.1.0.dist-info/WHEEL
subdownloader-2.1.0.dist-info/entry_points.txt
subdownloader-2.1.0.dist-info/metadata.json
subdownloader-2.1.0.dist-info/top_level.txt
