Metadata-Version: 2.0
Name: subdownloader
Version: 2.1.0
Summary: SubDownloader is a Free Open-Source tool written in PYTHON for automatic download/upload subtitles for videofiles (DIVX,MPEG,AVI,etc) and DVD's using fast hashing.
Home-page: https://github.com/subdownloader/subdownloader
Author: SubDownloader Developers
Author-email: anonymous.maarten@gmail.com
Maintainer: SubDownloader Developers
Maintainer-email: anonymous.maarten@gmail.com
License: GPL3
Download-URL: https://github.com/subdownloader/subdownloader/releases
Project-URL: Source Code, https://github.com/subdownloader/subdownloader
Project-URL: Bug Tracker, https://github.com/subdownloader/subdownloader/issues
Project-URL: Translations, https://github.com/subdownloader/subdownloader-i18n
Keywords: download,upload,automatic,subtitle,movie,video,film,search
Platform: UNKNOWN
Classifier: Topic :: Multimedia
Classifier: Topic :: Utilities
Classifier: Environment :: Console
Classifier: Environment :: X11 Applications :: Qt
Classifier: Development Status :: 4 - Beta
Classifier: Intended Audience :: End Users/Desktop
Classifier: License :: OSI Approved :: GNU General Public License v3 (GPLv3)
Classifier: Natural Language :: English
Classifier: Programming Language :: Python :: 3.5
Classifier: Programming Language :: Python :: 3.6
Classifier: Programming Language :: Python :: 3.7
Requires: argcomplete (>=1.7.0)
Requires: langdetect (>=1.0.7)
Requires: pymediainfo (>=2.1.6)
Requires: PyQt5 (>= 5.0.0)
Provides: subdownloader
Requires-Python: >=3.5.*, <4
